django_simple_robots-1.0.0.dist-info/DESCRIPTION.rst
django_simple_robots-1.0.0.dist-info/METADATA
django_simple_robots-1.0.0.dist-info/RECORD
django_simple_robots-1.0.0.dist-info/WHEEL
django_simple_robots-1.0.0.dist-info/metadata.json
django_simple_robots-1.0.0.dist-info/top_level.txt
simple_robots/__init__.py
simple_robots/views.py
simple_robots/__pycache__/__init__.cpython-34.pyc
simple_robots/__pycache__/tests.cpython-34.pyc
simple_robots/__pycache__/views.cpython-34.pyc
simple_robots/tests/__init__.py
simple_robots/tests/settings.py
simple_robots/tests/tests.py
simple_robots/tests/urls.py
simple_robots/tests/__pycache__/__init__.cpython-34.pyc
simple_robots/tests/__pycache__/settings.cpython-34.pyc
simple_robots/tests/__pycache__/tests.cpython-34.pyc
simple_robots/tests/__pycache__/urls.cpython-34.pyc
