Metadata-Version: 2.0
Name: django-simple-robots
Version: 1.0.0
Summary: Simple robots.txt file serving for web applications
Home-page: http://www.dabapps.com
Author: DabApps
Author-email: hello@dabapps.com
License: BSD
Platform: UNKNOWN
